LICENSE
README.md
setup.py
tap_exacttarget/__init__.py
tap_exacttarget/client.py
tap_exacttarget/dao.py
tap_exacttarget/filters.py
tap_exacttarget/fuel_overrides.py
tap_exacttarget/pagination.py
tap_exacttarget/state.py
tap_exacttarget/util.py
tap_exacttarget.egg-info/PKG-INFO
tap_exacttarget.egg-info/SOURCES.txt
tap_exacttarget.egg-info/dependency_links.txt
tap_exacttarget.egg-info/entry_points.txt
tap_exacttarget.egg-info/requires.txt
tap_exacttarget.egg-info/top_level.txt
tap_exacttarget/endpoints/__init__.py
tap_exacttarget/endpoints/campaigns.py
tap_exacttarget/endpoints/content_areas.py
tap_exacttarget/endpoints/data_extensions.py
tap_exacttarget/endpoints/emails.py
tap_exacttarget/endpoints/events.py
tap_exacttarget/endpoints/folders.py
tap_exacttarget/endpoints/list_sends.py
tap_exacttarget/endpoints/list_subscribers.py
tap_exacttarget/endpoints/lists.py
tap_exacttarget/endpoints/sends.py
tap_exacttarget/endpoints/subscribers.py
tap_exacttarget/schemas/campaigns.json
tap_exacttarget/schemas/content_areas.json
tap_exacttarget/schemas/definitions.json
tap_exacttarget/schemas/emails.json
tap_exacttarget/schemas/events.json
tap_exacttarget/schemas/folders.json
tap_exacttarget/schemas/list_sends.json
tap_exacttarget/schemas/list_subscribers.json
tap_exacttarget/schemas/lists.json
tap_exacttarget/schemas/sends.json
tap_exacttarget/schemas/subscribers.json